{
    "mission_start_time": "Mon May 11 14:51:35 2026",
    "target_nodes": [
        "A1791B16D5"
    ],
    "events": [
        {
            "time": "14:51:35",
            "type": "START",
            "details": "Hành trình bắt đầu. Điểm đích cuối: START"
        },
        {
            "time": "14:51:35",
            "type": "TURN_EXEC",
            "details": "Lệnh điều hướng: STRAIGHT tại START"
        },
        {
            "time": "14:52:07",
            "type": "RFID",
            "details": "Phát hiện Node: A"
        },
        {
            "time": "14:52:07",
            "type": "TURN_EXEC",
            "details": "Lệnh điều hướng: LEFT tại A"
        },
        {
            "time": "14:52:21",
            "type": "RFID",
            "details": "Phát hiện Node: B"
        },
        {
            "time": "14:52:23",
            "type": "TURN_EXEC",
            "details": "Lệnh điều hướng: RIGHT tại B"
        },
        {
            "time": "14:52:34",
            "type": "STOPPED",
            "details": "Mission dừng sớm hoặc bị hủy bởi người dùng."
        }
    ],
    "signs_detected": []
}