{
    "mission_start_time": "Mon May 11 13:41:56 2026",
    "target_nodes": [
        "A1791B16D5"
    ],
    "events": [
        {
            "time": "13:41:56",
            "type": "START",
            "details": "Hành trình bắt đầu. Điểm đích cuối: START"
        },
        {
            "time": "13:41:56",
            "type": "TURN_EXEC",
            "details": "Lệnh điều hướng: STRAIGHT tại START"
        },
        {
            "time": "13:42:27",
            "type": "RFID",
            "details": "Phát hiện Node: A"
        },
        {
            "time": "13:42:27",
            "type": "TURN_EXEC",
            "details": "Lệnh điều hướng: LEFT tại A"
        },
        {
            "time": "13:42:57",
            "type": "RFID",
            "details": "Phát hiện Node: B"
        },
        {
            "time": "13:42:57",
            "type": "TURN_EXEC",
            "details": "Lệnh điều hướng: RIGHT tại B"
        },
        {
            "time": "13:43:09",
            "type": "OBSTACLE",
            "details": "Phát hiện vật cản tại 9.9cm. Dừng quan sát 3s."
        },
        {
            "time": "13:43:12",
            "type": "OBSTACLE",
            "details": "Trường hợp 1: Đối đầu (vật tĩnh/xe khác dừng). Đang re-plan..."
        },
        {
            "time": "13:43:20",
            "type": "RFID",
            "details": "Phát hiện Node: B"
        },
        {
            "time": "13:43:20",
            "type": "TURN_EXEC",
            "details": "Lệnh điều hướng: RIGHT tại B"
        },
        {
            "time": "13:43:33",
            "type": "RFID",
            "details": "Phát hiện Node: C"
        },
        {
            "time": "13:43:33",
            "type": "TURN_EXEC",
            "details": "Lệnh điều hướng: LEFT tại C"
        },
        {
            "time": "13:44:17",
            "type": "RFID",
            "details": "Phát hiện Node: A"
        },
        {
            "time": "13:44:17",
            "type": "TURN_EXEC",
            "details": "Lệnh điều hướng: RIGHT tại A"
        },
        {
            "time": "13:44:28",
            "type": "STOPPED",
            "details": "Mission dừng sớm hoặc bị hủy bởi người dùng."
        }
    ],
    "signs_detected": [
        {
            "type": "straight",
            "confidence": 0.49140334129333496,
            "image_path": "data/sign_snapshots/straight_1778481767.jpg",
            "timestamp": "Mon May 11 13:42:47 2026"
        },
        {
            "type": "parking",
            "confidence": 0.4154864549636841,
            "image_path": "data/sign_snapshots/parking_1778481775.jpg",
            "timestamp": "Mon May 11 13:42:55 2026"
        },
        {
            "type": "left",
            "confidence": 0.4163707494735718,
            "image_path": "data/sign_snapshots/left_1778481778.jpg",
            "timestamp": "Mon May 11 13:42:58 2026"
        },
        {
            "type": "right",
            "confidence": 0.42804214358329773,
            "image_path": "data/sign_snapshots/right_1778481819.jpg",
            "timestamp": "Mon May 11 13:43:39 2026"
        }
    ]
}